demonstrable/__init__.py
demonstrable-0.0.2.dist-info/LICENSE
demonstrable-0.0.2.dist-info/METADATA
demonstrable-0.0.2.dist-info/WHEEL
demonstrable-0.0.2.dist-info/top_level.txt
demonstrable-0.0.2.dist-info/RECORD
